hpc_plotter/__init__.py
hpc_plotter/create_argparse.py
hpc_plotter/main.py
hpc_plotter/plotting.py
hpc_plotter/timer.py
hpc_plotter/utils.py
hpc_plotter-0.1.3.dist-info/LICENSE
hpc_plotter-0.1.3.dist-info/METADATA
hpc_plotter-0.1.3.dist-info/WHEEL
hpc_plotter-0.1.3.dist-info/entry_points.txt
hpc_plotter-0.1.3.dist-info/top_level.txt
hpc_plotter-0.1.3.dist-info/RECORD
